cleancopy/__init__.py
cleancopy/_cst/__init__.py
cleancopy/_cst/abstractifier.py
cleancopy/_cst/treesitter_.py
cleancopy/ast.py
cleancopy/cst.py
cleancopy/exceptions.py
cleancopy/py.typed
cleancopy/spectypes.py
cleancopy/utils.py
pycleancopy-2025.8.29.0.dist-info/METADATA
pycleancopy-2025.8.29.0.dist-info/WHEEL
pycleancopy-2025.8.29.0.dist-info/entry_points.txt
pycleancopy-2025.8.29.0.dist-info/RECORD
