Metadata-Version: 2.1
Name: pycleancopy
Version: 2025.8.29.0
Summary: Python bindings to the cleancopy lightweight markup language
Requires-Python: >=3.12
Requires-Dist: docnote>=2025.8.5.0
Requires-Dist: tree-sitter>=0.22.3
Requires-Dist: tree-sitter-cleancopy>=0.0.18
